odoo8_addon_partner_address_street3-8.0.0.1.0.99.dev10-py2.7-nspkg.pth
odoo_addons/partner_address_street3/__openerp__.py
odoo_addons/partner_address_street3/__init__.py
odoo_addons/partner_address_street3/README.rst
odoo_addons/partner_address_street3/view/partner_view.xml
odoo_addons/partner_address_street3/i18n/it.po
odoo_addons/partner_address_street3/i18n/es.po
odoo_addons/partner_address_street3/i18n/sl.po
odoo_addons/partner_address_street3/i18n/da.po
odoo_addons/partner_address_street3/i18n/nl.po
odoo_addons/partner_address_street3/i18n/de.po
odoo_addons/partner_address_street3/i18n/fr.po
odoo_addons/partner_address_street3/i18n/pt_BR.po
odoo_addons/partner_address_street3/i18n/fi.po
odoo_addons/partner_address_street3/i18n/hr_HR.po
odoo_addons/partner_address_street3/model/partner.py
odoo_addons/partner_address_street3/model/__init__.py
odoo_addons/partner_address_street3/tests/__init__.py
odoo_addons/partner_address_street3/tests/test_street_3.py
odoo_addons/partner_address_street3/static/description/icon.png
odoo8_addon_partner_address_street3-8.0.0.1.0.99.dev10.dist-info/top_level.txt
odoo8_addon_partner_address_street3-8.0.0.1.0.99.dev10.dist-info/WHEEL
odoo8_addon_partner_address_street3-8.0.0.1.0.99.dev10.dist-info/RECORD
odoo8_addon_partner_address_street3-8.0.0.1.0.99.dev10.dist-info/metadata.json
odoo8_addon_partner_address_street3-8.0.0.1.0.99.dev10.dist-info/DESCRIPTION.rst
odoo8_addon_partner_address_street3-8.0.0.1.0.99.dev10.dist-info/METADATA
odoo8_addon_partner_address_street3-8.0.0.1.0.99.dev10.dist-info/namespace_packages.txt
